CHANGELOG.rst
MANIFEST.in
README.rst
setup.py
echarts_countries_pypkg/__init__.py
echarts_countries_pypkg/_version.py
echarts_countries_pypkg.egg-info/PKG-INFO
echarts_countries_pypkg.egg-info/SOURCES.txt
echarts_countries_pypkg.egg-info/dependency_links.txt
echarts_countries_pypkg.egg-info/not-zip-safe
echarts_countries_pypkg.egg-info/requires.txt
echarts_countries_pypkg.egg-info/top_level.txt
echarts_countries_pypkg/resources/registry.json
echarts_countries_pypkg/resources/echarts-countries-js/Afghanistan.js
echarts_countries_pypkg/resources/echarts-countries-js/Albania.js
echarts_countries_pypkg/resources/echarts-countries-js/Algeria.js
echarts_countries_pypkg/resources/echarts-countries-js/Andorra.js
echarts_countries_pypkg/resources/echarts-countries-js/Angola.js
echarts_countries_pypkg/resources/echarts-countries-js/Anguilla.js
echarts_countries_pypkg/resources/echarts-countries-js/Antigua_and_Barbuda.js
echarts_countries_pypkg/resources/echarts-countries-js/Argentina.js
echarts_countries_pypkg/resources/echarts-countries-js/Armenia.js
echarts_countries_pypkg/resources/echarts-countries-js/Australia.js
echarts_countries_pypkg/resources/echarts-countries-js/Austria.js
echarts_countries_pypkg/resources/echarts-countries-js/Azerbaijan.js
echarts_countries_pypkg/resources/echarts-countries-js/Bahrain.js
echarts_countries_pypkg/resources/echarts-countries-js/Bangladesh.js
echarts_countries_pypkg/resources/echarts-countries-js/Barbados.js
echarts_countries_pypkg/resources/echarts-countries-js/Belarus.js
echarts_countries_pypkg/resources/echarts-countries-js/Belgium.js
echarts_countries_pypkg/resources/echarts-countries-js/Belize.js
echarts_countries_pypkg/resources/echarts-countries-js/Benin.js
echarts_countries_pypkg/resources/echarts-countries-js/Bermuda.js
echarts_countries_pypkg/resources/echarts-countries-js/Bhutan.js
echarts_countries_pypkg/resources/echarts-countries-js/Bolivia.js
echarts_countries_pypkg/resources/echarts-countries-js/Bosnia_and_Herzegovina.js
echarts_countries_pypkg/resources/echarts-countries-js/Botswana.js
echarts_countries_pypkg/resources/echarts-countries-js/Brazil.js
echarts_countries_pypkg/resources/echarts-countries-js/British_Indian_Ocean_Territory.js
